tnfepitope/blast_binaries/linux/blastp
tnfepitope/blast_binaries/mac/blastp
tnfepitope/blast_binaries/windows/blastp.exe
tnfepitope/blast_binaries/windows/nghttp2.dll
tnfepitope/blast_db/humandb.phr
tnfepitope/blast_db/humandb.pin
tnfepitope/blast_db/humandb.pog
tnfepitope/blast_db/humandb.psd
tnfepitope/blast_db/humandb.psi
tnfepitope/blast_db/humandb.psq
tnfepitope/blast_db/mouse_db.phr
tnfepitope/blast_db/mouse_db.pin
tnfepitope/blast_db/mouse_db.pog
tnfepitope/blast_db/mouse_db.psd
tnfepitope/blast_db/mouse_db.psi
tnfepitope/blast_db/mouse_db.psq
tnfepitope/model/alt_mouse_model.pkl
tnfepitope/model/main_human_model.pkl
tnfepitope/python_scripts/__init__.py
tnfepitope/python_scripts/tnfepitope.py
tnfepitope-1.4.dist-info/LICENSE
tnfepitope-1.4.dist-info/METADATA
tnfepitope-1.4.dist-info/WHEEL
tnfepitope-1.4.dist-info/entry_points.txt
tnfepitope-1.4.dist-info/top_level.txt
tnfepitope-1.4.dist-info/RECORD
