Metadata-Version: 2.1
Name: tnfepitope
Version: 1.4
Summary: A webserver for prediction of TNF inducing epitopes
Home-page: https://gitlab.com/raghavalab/tnfepitope
Requires-Python: >=3.6
Requires-Dist: numpy
Requires-Dist: pandas
Requires-Dist: scikit-learn
Requires-Dist: argparse
